artorias/__init__.py
artorias/commands/__init__.py
artorias/commands/create.py
artorias/commands/main.py
artorias/flask/__init__.py
artorias/flask/celery.py
artorias/flask/core.py
artorias/flask/exception.py
artorias/flask/exts.py
artorias/flask/json.py
artorias/flask/jwt.py
artorias/flask/pydantic.py
artorias/flask/settings.py
artorias/flask/sqlalchemy.py
artorias/flask/utils.py
artorias/utils/__init__.py
artorias-0.1.7.dist-info/METADATA
artorias-0.1.7.dist-info/WHEEL
artorias-0.1.7.dist-info/entry_points.txt
artorias-0.1.7.dist-info/RECORD
