Metadata-Version: 2.1
Name: artorias
Version: 0.1.7
Summary: My web utilities
Author: Abyssknight
Author-email: 501835725@qq.com
Requires-Python: >=3.12,<4.0
Classifier: Programming Language :: Python :: 3
Classifier: Programming Language :: Python :: 3.12
Requires-Dist: celery
Requires-Dist: flask-cors
Requires-Dist: flask-jwt-extended
Requires-Dist: flask-migrate
Requires-Dist: flask-sqlalchemy
Requires-Dist: pydantic-settings
Requires-Dist: redis-om
Requires-Dist: sqlalchemy
Requires-Dist: typer[all]
